pyxlart/__init__.py
pyxlart/border_logic.py
pyxlart/cell_address_model.py
pyxlart/column_letter_logic.py
pyxlart/column_letter_range.py
pyxlart/graph_paper_renderer.py
pyxlart-103.1.0.dist-info/METADATA
pyxlart-103.1.0.dist-info/WHEEL
pyxlart-103.1.0.dist-info/licenses/LICENSE
pyxlart-103.1.0.dist-info/RECORD
