Metadata-Version: 2.4
Name: pyxlart
Version: 103.1.0
Summary: Renderer for Excel.
Project-URL: Repository, https://github.com/muzudho/pyxlart.git
Author-email: "TAKAHASHI Satoshi (Handle Name:むずでょ)" <muzudho1@gmail.com>
Maintainer-email: "TAKAHASHI Satoshi (Handle Name:むずでょ)" <muzudho1@gmail.com>
License: MIT License
License-File: LICENSE
Keywords: excel
Classifier: Programming Language :: Python
Requires-Dist: openpyxl>=3.1.5
